cryptocompare/__init__.py
cryptocompare/cryptocompare.py
cryptocompare-0.7.4.dist-info/LICENSE
cryptocompare-0.7.4.dist-info/METADATA
cryptocompare-0.7.4.dist-info/WHEEL
cryptocompare-0.7.4.dist-info/top_level.txt
cryptocompare-0.7.4.dist-info/RECORD
