Metadata-Version: 2.1
Name: cryptocompare
Version: 0.7.4
Summary: Wrapper for CryptoCompare.com
Home-page: https://github.com/lagerfeuer/cryptocompare
Author: lagerfeuer
Author-email: lukas.deutz@mailfence.com
License: MIT
Keywords: crypto cryptocurrency wrapper cryptocompare
Platform: UNKNOWN
Classifier: Programming Language :: Python :: 3
Requires-Python: >=3
Requires-Dist: requests
